wpget/__init__.py
wpget/cli.py
wpget-0.1.5.dist-info/METADATA
wpget-0.1.5.dist-info/WHEEL
wpget-0.1.5.dist-info/entry_points.txt
wpget-0.1.5.dist-info/licenses/LICENSE
wpget-0.1.5.dist-info/RECORD
