Metadata-Version: 2.3
Name: wpget
Version: 0.1.5
Summary: A tool for downloading all posts from a WordPress website via public JSON API
Project-URL: Homepage, https://pypi.org/project/wpget
Project-URL: Repository, https://github.com/seanghay/wpget
Author-email: Seanghay Yath <seanghay.dev@gmail.com>
License:                                  Apache License
License-File: LICENSE
Classifier: Development Status :: 4 - Beta
Classifier: Intended Audience :: Developers
Classifier: License :: OSI Approved :: MIT License
Classifier: Programming Language :: Python :: 3.8
Classifier: Topic :: Scientific/Engineering :: Artificial Intelligence
Requires-Python: >=3.8
Requires-Dist: chardet
Requires-Dist: fake-useragent
Requires-Dist: requests
Requires-Dist: tqdm
